cpmaxToolbox/FilterTool.py
cpmaxToolbox/SCADA.py
cpmaxToolbox/__init__.py
cpmaxToolbox-0.1.2.1636701193.dist-info/LICENSE
cpmaxToolbox-0.1.2.1636701193.dist-info/METADATA
cpmaxToolbox-0.1.2.1636701193.dist-info/WHEEL
cpmaxToolbox-0.1.2.1636701193.dist-info/top_level.txt
cpmaxToolbox-0.1.2.1636701193.dist-info/RECORD
