Metadata-Version: 2.1
Name: cpmaxToolbox
Version: 0.1.2.1636701193
Summary: Toolbox for cp.max Rotortechnik GmbH & Co. KG
Home-page: https://github.com/JRoseCPMax/cpmax_toolbox
Author: Jonas Rose
Author-email: j.rose@cpmax.com
License: GPLv3
Platform: UNKNOWN
Classifier: License :: OSI Approved :: GNU General Public License v3 or later (GPLv3+)
Classifier: Programming Language :: Python :: 3
Classifier: Programming Language :: Python :: 3.9
Classifier: Development Status :: 4 - Beta
Classifier: Topic :: Scientific/Engineering
Requires-Python: >=3.0
License-File: LICENSE
Requires-Dist: pandas
Requires-Dist: numpy
Requires-Dist: rich
Requires-Dist: scipy (==1.7.2)
